minwei_tools/__init__.py
minwei_tools/async_dotter.py
minwei_tools/dotter.py
minwei_tools/dotter_style.py
minwei_tools/rs_result.py
minwei_tools/server.py
minwei_tools/uv_doc.py
minwei_tools-0.1.20.dist-info/licenses/LICENSE
minwei_tools-0.1.20.dist-info/METADATA
minwei_tools-0.1.20.dist-info/WHEEL
minwei_tools-0.1.20.dist-info/entry_points.txt
minwei_tools-0.1.20.dist-info/top_level.txt
minwei_tools-0.1.20.dist-info/RECORD
