Metadata-Version: 2.4
Name: minwei-tools
Version: 0.1.20
Summary: Some useful tools for Python development by MinWei
Home-page: https://github.com/OuYangMinOa/minwei_tools
Author: OUYANGMINWEI
Author-email: OUYANGMINWEI <wesley91345@gmail.com>
Classifier: Programming Language :: Python :: 3
Classifier: Operating System :: OS Independent
Requires-Python: >=3.9
License-File: LICENSE
Requires-Dist: colorama>=0.4.6
Requires-Dist: flask>=2.2.5
Dynamic: author
Dynamic: home-page
Dynamic: license-file
Dynamic: requires-python
